{"chunk_definitions":[{"row":9,"row_count":1,"visible":true,"expansion_state":0,"options":{"engine":"r","label":"setup","include":false},"document_id":"7FD8F0FD","chunk_id":"csetup_chunk","chunk_label":"setup"},{"row":25,"row_count":1,"visible":true,"expansion_state":0,"options":{"engine":"r","label":"unnamed-chunk-8"},"document_id":"7FD8F0FD","chunk_id":"cbmz4slellkau","chunk_label":"unnamed-chunk-2"},{"row":30,"row_count":1,"visible":true,"expansion_state":0,"options":{"engine":"r","label":"unnamed-chunk-14"},"document_id":"7FD8F0FD","chunk_id":"cir3fe03tpduo","chunk_label":"unnamed-chunk-3"}],"doc_write_time":1695796999,"working_dir":null,"default_chunk_options":{"echo":true},"chunk_rendered_width":414}